{
    "Contrato Social": [
        "nome_companhia, cnpj_companhia",
        "junta_comercial, data_ata, numero_registro_ata",
        "data_contrato",
        "consolidacao",
        "representacao",
        "nome_administradores, cpf_administradores, mandato_administradores",
        "vedacao",
        "garantias",
        "vedacao1",
        "obrigacoes",
        "alienacao",
        "movimentacao",
        "procuracao"
    ],
    "Procura\u00e7\u00e3o PJ": [
        "nome_companhia, cnpj_companhia",
        "outorgantes",
        "registro",
        "outorgantes1",
        "data_procuracao",
        "validade",
        "representacao_isolada",
        "representacao_conjunta",
        "outorgados",
        "outogardos_geral",
        "grupo_poderes",
        "assina_poderes",
        "72_poderes"
    ],
    "Estatuto Social": [
        "nome_companhia, cnpj_companhia",
        "junta_comercial, data_registro, numero_registro",
        "data_assembleia",
        "assinatura",
        "representacao",
        "vedacao",
        "garantia_terceiros",
        "obrigacoes",
        "procuracao"
    ],
    "Elei\u00e7\u00e3o de Diretoria": [
        "nome_companhia, cnpj_companhia",
        "junta_comercial, data_ata, numero_registro_ata",
        "data_assembleia",
        "periodo_mandato",
        "diretores_eleitos, cpf_eleitos, diretoria_ratificada"
    ],
    "Procura\u00e7\u00e3o PF": [
        "nome_outorgante, cpf_outorgante",
        "numero_livro, numero_folhas",
        "assinante_digital",
        "data_procuracao",
        "validade",
        "representacao_isolada",
        "representacao_conjunta",
        "nome_outorgados, cpf_outorgados",
        "assina_poderes",
        "72_poderes"
    ]
}